datamazing/__init__.py
datamazing/_conform.py
datamazing/pandas/__init__.py
datamazing/pandas/datacollection/__init__.py
datamazing/pandas/io.py
datamazing/pandas/testing/__init__.py
datamazing/pandas/testing/assertions.py
datamazing/pandas/testing/data.py
datamazing/pandas/testing/mock.py
datamazing/pandas/transformations/__init__.py
datamazing/pandas/transformations/basic.py
datamazing/pandas/transformations/grouping.py
datamazing/pandas/transformations/merging.py
datamazing/pandas/transformations/reindexing.py
datamazing/pandas/transformations/resampling.py
datamazing/pandas/types/__init__.py
datamazing/pandas/types/time_interval.py
datamazing/pandas/types/time_travel.py
datamazing/pyspark/__init__.py
datamazing/pyspark/functions/__init__.py
datamazing/pyspark/functions/time.py
datamazing/pyspark/testing/__init__.py
datamazing/pyspark/testing/assertions.py
datamazing/pyspark/testing/data.py
datamazing/pyspark/transformations/__init__.py
datamazing/pyspark/transformations/grouping.py
datamazing-5.2.0.dist-info/METADATA
datamazing-5.2.0.dist-info/WHEEL
datamazing-5.2.0.dist-info/RECORD
