Metadata-Version: 2.4
Name: datamazing
Version: 5.2.0
Summary: Package for working with pandas Dataset, but with specialized functions used for Energinet
Author: Team Enigma
Author-email: enigma@energinet.dk
Requires-Python: >=3.10
Classifier: Programming Language :: Python :: 3
Classifier: Programming Language :: Python :: 3.10
Classifier: Programming Language :: Python :: 3.11
Classifier: Programming Language :: Python :: 3.12
Classifier: Programming Language :: Python :: 3.13
Classifier: Programming Language :: Python :: 3.14
